<?xml version="1.0" encoding="utf-8"?>
<Defs>
  <ThingDef ParentName="BuildingBase">
    <defName>SailChiller</defName>
    <label>sail chiller</label>
    <description>A large improvised wind-catching sail that cools buildings by water evaporation. It should be refueled with water daily.</description>
    <category>Building</category>
    <graphicData>
      <texPath>Things/Building/Misc/SailChillerA</texPath>
      <graphicClass>Graphic_Multi</graphicClass>
      <drawRotated>false</drawRotated>
      <allowFlip>true</allowFlip>
      <linkType>None</linkType>
      <linkFlags>
        <li>Wall</li>
        <li>Rock</li>
      </linkFlags>
      <drawSize>(4,4)</drawSize>
      <drawOffset>(0.65,0,0.65)</drawOffset>
      <drawOffsetWest>(-0.65,0,0.65)</drawOffsetWest>
      <color>(139,122,87)</color>
      <damageData>
        <rect>(2,0.15,1,1.4)</rect>
      </damageData>
      <shaderType>Cutout</shaderType>
    </graphicData>
    <size>(3,3)</size>
    <uiIconPath>Things/Building/Misc/SailChillerAIcon</uiIconPath>
    <altitudeLayer>Building</altitudeLayer>
    <passability>PassThroughOnly</passability>
    <pathCost>90</pathCost>
    <tickerType>Normal</tickerType>
    <drawerType>RealtimeOnly</drawerType>
    <fillPercent>0.40</fillPercent>
    <statBases>
      <MaxHitPoints>100</MaxHitPoints>
      <WorkToBuild>1500</WorkToBuild>
      <Flammability>1</Flammability>
    </statBases>
    <selectable>true</selectable>
    <costList>
      <WoodLog>200</WoodLog>
    </costList>
    <stuffCategories>
      <li>Leathery</li>
    </stuffCategories>
    <costStuffCount>150</costStuffCount>
    <soundImpactDefault>BulletImpact_Ground</soundImpactDefault>
    <leaveResourcesWhenKilled>false</leaveResourcesWhenKilled>
    <resourcesFractionWhenDeconstructed>0</resourcesFractionWhenDeconstructed>
    <placeWorkers>
      <li>PlaceWorker_CoolerSimple</li>
    </placeWorkers>
    <drawPlaceWorkersWhileSelected>true</drawPlaceWorkersWhileSelected>
    <comps>
      <li Class="CompProperties_HeatPusher">
        <compClass>CompHeatPusherPowered</compClass>
        <heatPerSecond>-25</heatPerSecond>
        <heatPushMinTemperature>7</heatPushMinTemperature>
      </li>
    </comps>
    <designationCategory>Temperature</designationCategory>
    <designationHotKey>Misc3</designationHotKey>
    <researchPrerequisites>
      <li>PassiveCooler</li>
    </researchPrerequisites>
  </ThingDef>
</Defs>